pypoh/__init__.py
pypoh/pypoh.py
pypoh/test.py
pypoh-0.105.dist-info/LICENSE.txt
pypoh-0.105.dist-info/METADATA
pypoh-0.105.dist-info/WHEEL
pypoh-0.105.dist-info/top_level.txt
pypoh-0.105.dist-info/RECORD
